graphql_validate/__init__.py
graphql_validate/__main__.py
graphql_validate/cli.py
graphql_validate/logging.py
graphql_validate/schemas.py
graphql_validate/checks/__init__.py
graphql_validate/checks/documentation.py
graphql_validate/checks/issues.py
graphql_validate/checks/structure.py
graphql_validate-0.0.6.dist-info/METADATA
graphql_validate-0.0.6.dist-info/RECORD
graphql_validate-0.0.6.dist-info/WHEEL
graphql_validate-0.0.6.dist-info/entry_points.txt
graphql_validate-0.0.6.dist-info/top_level.txt
